<?xml version="1.0" encoding="windows-1251"?>
<questestinterop><item ident="QUE108"><presentation><material><mattext>To get an opportunity to manage component parameters via the visual interface, it is necessary to describe these parameters in file with the following name:</mattext></material><response_lid ident="LID108" rcardinality="Single"><render_choice><response_label ident="ANS1479"><material><mattext>.default.php </mattext></material></response_label><response_label ident="ANS1480"><material><mattext>description.php</mattext></material></response_label><response_label ident="ANS1481"><material><mattext>.description.php</mattext></material></response_label><response_label ident="ANS1482"><material><mattext>/component_name/description.php</mattext></material></response_label></render_choice></response_lid></presentation><resprocessing><respcondition><conditionvar><varequal respident="LID108">ANS1481</varequal></conditionvar><setvar>10</setvar></respcondition></resprocessing><bitrix><description></description><description_type>text</description_type><self>Y</self><sort>50</sort><active>Y</active></bitrix></item></questestinterop>