<?xml version="1.0" encoding="windows-1251"?>
<content type="LES"><id>369</id>
<timestamp_x>1162482874</timestamp_x>
<date_create>1153482876</date_create>
<created_by>1837</created_by>
<active>Y</active>
<course_id>10</course_id>
<chapter_id>138</chapter_id>
<name>Managing via the system interface</name>
<sort>200</sort>
<preview_picture></preview_picture>
<preview_text></preview_text>
<preview_text_type>text</preview_text_type>
<detail_picture></detail_picture>
<detail_text><![CDATA[
<p>The page or web-browser title can be modified the following ways:</p>

<ul>
  <li>durin the page creating or edditing in the visual HTML editor mode: 
    <ul>
      <li>the document title is assigned in the <strong>Page title </strong>field: 
        <br />
      
        <br />
      <a href="javascript:ShowImg('/images/integration_course_en/title/html_mode.png',450,230,'Page title')"><img src="cid:resources/res33/jGcLS.nwK8k.html_mode_s.png" height="154" alt="Click to enlarge" hspace="0" width="300" border="0"/></a> </li>
    
      <li>the page property <strong>Additional title of page (for browser window)</strong> is used for defining web-browser window title: 
        <br />
      
        <br />
      <a href="javascript:ShowImg('/images/integration_course_en/title/html_mode_add_title.png',450,334,'Web-browser window title')"><img src="cid:resources/res33/bS84X.OSQhW.html_mode_add_title_s.png" height="223" alt="Click to enlarge" hspace="0" width="300" border="0"/></a> </li>
    </ul>
  
    <p>Preliminapy the &quot;Additional title of page (for browser window)&quot; property (the property with the &quot;title&quot; code)must be created. This property is included in product supply and is utilize for syte pages by defaulte. More detailed information on page property management is available in the &quot;Page and section properties&quot;.</p>
  
    <p>Assigned properties values are saved automatically in the page code. </p>
  </li>

  <li>during editing page &quot;as text&quot;: 
    <br />
  
    <br />
  <a href="javascript:ShowImg('/images/integration_course_en/title/txt_mode.png',450,330,'Page and web-browser window titles')"><img src="cid:resources/res33/dvYmM.6Z1W8.txt_mode_s.png" height="220" alt="Click to enlarge" hspace="0" width="300" border="0"/></a> </li>

  <li>during editing page &quot;as PHP&quot;: 
    <br />
  
    <br />
  <a href="javascript:ShowImg('/images/integration_course_en/title/php_mode.png',450,198,'Page and web-browser window titles')"><img src="cid:resources/res33/jYCM3.SOZHI.php_mode_s.png" height="132" alt="Click to enlarge" hspace="0" width="300" border="0"/></a> </li>
</ul>

<div class="hint">Using the folder properties you can assign <strong>Additional title of page (for browser window)</strong> that will be used for all stored in this folder pages by defaulte. 
  <p>
    <table>
      <tbody>
        <tr><td><a href="javascript:ShowImg('/images/integration_course_en/title/fold_add_title.png',450,287,'Folder properties')"><img src="cid:resources/res33/8TLPV.jWqj1.fold_add_title_s.png" height="128" alt="Click to enlarge" hspace="0" width="200" border="0"/></a> </td><td>&nbsp;</td><td><a href="javascript:ShowImg('/images/integration_course_en/title/defaulte_title.png',450,383,'Web-browser window defaulte title')"><img src="cid:resources/res33/lb1tj.ONGnz.defaulte_title_s.png" height="128" alt="Click to enlarge" hspace="0" width="151" border="0"/></a> </td></tr>
      </tbody>
    </table>
  </p>
</div>
]]></detail_text>
<detail_text_type>html</detail_text_type>
</content>